{
    "manifestVersion": 2,
    "installedAssets": [
        {
            "name": "POLYGON - Fantasy Kingdom",
            "id": "164532",
            "versionId": "1.02",
            "versionNumber": 577178
        },
        {
            "name": "Help me Place! Editor Prefab Placement Assist",
            "id": "191351",
            "versionId": "1.2",
            "versionNumber": 607525
        },
        {
            "name": "Csharp Wizard",
            "id": "104887",
            "versionId": "1.4",
            "versionNumber": 484477
        },
        {
            "name": "Odin - Inspector and Serializer",
            "id": "89041",
            "versionId": "2.1.10",
            "versionNumber": 507587
        },
        {
            "name": "Real Ivy 2 Procedural Ivy Generator",
            "id": "181402",
            "versionId": "2.0.6",
            "versionNumber": 571663
        }
    ]
}